Metadata-Version: 2.4
Name: mseep-aiohttp-mcp
Version: 1.0.0
Summary: Tools for building Model Context Protocol (MCP) servers on top of aiohttp
Home-page: 
Author: mseep
Author-email: support@skydeck.ai
Maintainer: mseep
Maintainer-email: support@skydeck.ai
Keywords: mseep,mcp,model-context-protocol,aiohttp,ai,llm,server,async
Classifier: Programming Language :: Python :: 3
Classifier: License :: OSI Approved :: MIT License
Classifier: Operating System :: OS Independent
Requires-Python: >=3.6
License-File: LICENSE
Requires-Dist: aiohttp<4.0.0,>=3.9.0
Requires-Dist: aiohttp-sse<3.0.0,>=2.2.0
Requires-Dist: anyio<5.0.0,>=4.9.0
Requires-Dist: mcp<2.0.0,>=1.8.0
Dynamic: author
Dynamic: author-email
Dynamic: classifier
Dynamic: description
Dynamic: description-content-type
Dynamic: keywords
Dynamic: license-file
Dynamic: maintainer
Dynamic: maintainer-email
Dynamic: requires-dist
Dynamic: requires-python
Dynamic: summary
